[
    {
        "description": "connector HV BNC (R316553)",
        "location": "",
        "quantity": "1.00",
        "stockcode": "10028"
    },
    {
        "description": "HV BNC socket (Radial)",
        "location": "",
        "quantity": "1.00",
        "stockcode": "10066"
    },
    {
        "description": "BNC bulkhead connector",
        "location": "",
        "quantity": "2.00",
        "stockcode": "10197"
    },
    {
        "description": "25way gender changer",
        "location": "",
        "quantity": "1.00",
        "stockcode": "10266"
    },
    {
        "description": "M300 Curved Mirror.  UV-AL coating",
        "location": "",
        "quantity": "1.00",
        "stockcode": "11038"
    },
    {
        "description": "M300 Mirror Retaining Block",
        "location": "",
        "quantity": "1.00",
        "stockcode": "11124"
    },
    {
        "description": "Pin",
        "location": "",
        "quantity": "1.00",
        "stockcode": "11223"
    },
    {
        "description": "Pressure plate spring",
        "location": "",
        "quantity": "1.00",
        "stockcode": "11225"
    },
    {
        "description": "M4 Ball ended grub screw ( free issue 99022)",
        "location": "",
        "quantity": "1.00",
        "stockcode": "11250"
    },
    {
        "description": "Plane mirror 50x50x3mm  Al/MgF2",
        "location": "",
        "quantity": "1.00",
        "stockcode": "13123"
    },
    {
        "description": "PLAIN MIRROR WEDGE",
        "location": "",
        "quantity": "1.00",
        "stockcode": "17250"
    },
    {
        "description": "M4 clinch nut insert",
        "location": "",
        "quantity": "2.00",
        "stockcode": "19055"
    },
    {
        "description": "Fastener self clinch M4",
        "location": "",
        "quantity": "6.00",
        "stockcode": "19086"
    },
    {
        "description": "FSM150Xe Iris",
        "location": "",
        "quantity": "1.00",
        "stockcode": "19320"
    },
    {
        "description": "Bosch 6mm groove M4 'T' nut",
        "location": "",
        "quantity": "8.00",
        "stockcode": "19346"
    },
    {
        "description": "Bosch 20mm extrusion end cap (each)",
        "location": "",
        "quantity": "8.00",
        "stockcode": "19347"
    },
    {
        "description": "Bosch handle 8/10mm Groove version",
        "location": "",
        "quantity": "2.00",
        "stockcode": "19378"
    },
    {
        "description": "M6 taptite screw",
        "location": "",
        "quantity": "20.00",
        "stockcode": "19421"
    },
    {
        "description": "Wooden packing crate (Kema UMS). INTERNAL 75x75x51cm",
        "location": "",
        "quantity": "1.00",
        "stockcode": "25013"
    },
    {
        "description": "SAC system UMS small plain mirror fixed plate",
        "location": "",
        "quantity": "1.00",
        "stockcode": "41475"
    },
    {
        "description": "SAC UMS plain mirror cover",
        "location": "",
        "quantity": "1.00",
        "stockcode": "41476"
    },
    {
        "description": "SAC system UMS small plain mirror back plate",
        "location": "",
        "quantity": "1.00",
        "stockcode": "41477"
    },
    {
        "description": "M4 x 20 ball ended grub screw (fi 99061)",
        "location": "",
        "quantity": "2.00",
        "stockcode": "41478"
    },
    {
        "description": "SAC system UMS large curved mirror bracket",
        "location": "",
        "quantity": "1.00",
        "stockcode": "41484"
    },
    {
        "description": "SAC system UMS small plain mirror bracket",
        "location": "",
        "quantity": "1.00",
        "stockcode": "41485"
    },
    {
        "description": "SAC UMS sealing 'O' ring (pack of 50)",
        "location": "",
        "quantity": "1.00",
        "stockcode": "41495"
    },
    {
        "description": "Accent MVSS thrust washer",
        "location": "",
        "quantity": "1.00",
        "stockcode": "42732"
    },
    {
        "description": "UMS launch optic",
        "location": "",
        "quantity": "1.00",
        "stockcode": "43146"
    },
    {
        "description": "UMS base plate",
        "location": "",
        "quantity": "1.00",
        "stockcode": "43147"
    },
    {
        "description": "Bosch, 20x20, 4 channel x 610mm long",
        "location": "",
        "quantity": "4.00",
        "stockcode": "43148"
    },
    {
        "description": "Bosch",
        "location": "",
        "quantity": "6.00",
        "stockcode": "43149"
    },
    {
        "description": "Bosch",
        "location": "",
        "quantity": "4.00",
        "stockcode": "43150"
    },
    {
        "description": "Kema ums panel",
        "location": "",
        "quantity": "2.00",
        "stockcode": "43151"
    },
    {
        "description": "UMS entrance panel",
        "location": "",
        "quantity": "1.00",
        "stockcode": "43152"
    },
    {
        "description": "Kema UMS clamp",
        "location": "",
        "quantity": "2.00",
        "stockcode": "43156"
    },
    {
        "description": "Rail for UMS",
        "location": "",
        "quantity": "1.00",
        "stockcode": "43158"
    },
    {
        "description": "UMS internal cover",
        "location": "",
        "quantity": "1.00",
        "stockcode": "43161"
    },
    {
        "description": "Bosch 20x20",
        "location": "",
        "quantity": "2.00",
        "stockcode": "43162"
    },
    {
        "description": "Kema ums lid panel",
        "location": "",
        "quantity": "1.00",
        "stockcode": "43164"
    },
    {
        "description": "KEMA UMS Connector Panel Painted",
        "location": "",
        "quantity": "1.00",
        "stockcode": "43165_P1"
    },
    {
        "description": "HV feed through",
        "location": "",
        "quantity": "1.00",
        "stockcode": "43166"
    },
    {
        "description": "UMS entrance plate",
        "location": "",
        "quantity": "1.00",
        "stockcode": "43167"
    },
    {
        "description": "Kema ums panel",
        "location": "",
        "quantity": "1.00",
        "stockcode": "43168"
    },
    {
        "description": "UMS locator plates",
        "location": "",
        "quantity": "4.00",
        "stockcode": "43169"
    }
]