[
    {
        "description": "Connector 9 Way 'D' Plug",
        "location": "",
        "quantity": "1.00",
        "stockcode": "10086"
    },
    {
        "description": "Connector 9 Way 'D' Metal Case",
        "location": "",
        "quantity": "1.00",
        "stockcode": "10111"
    },
    {
        "description": "M300 microswitch",
        "location": "",
        "quantity": "2.00",
        "stockcode": "11001"
    },
    {
        "description": "T300X unislide switch block",
        "location": "",
        "quantity": "1.00",
        "stockcode": "11008"
    },
    {
        "description": "T300X(100) spacer plate",
        "location": "",
        "quantity": "1.00",
        "stockcode": "11011"
    },
    {
        "description": "T300X END BLOCK B",
        "location": "",
        "quantity": "1.00",
        "stockcode": "11013"
    },
    {
        "description": "T300X END BLOCK A",
        "location": "",
        "quantity": "1.00",
        "stockcode": "11014"
    },
    {
        "description": "T300X(100) LEADSCREW BLOCK",
        "location": "",
        "quantity": "1.00",
        "stockcode": "11040"
    },
    {
        "description": "M3 inserts in slider (lead screw min. 5mm from end of track)",
        "location": "",
        "quantity": "1.00",
        "stockcode": "11042"
    },
    {
        "description": "Coupling rigid 1/4\" bore x 3/4\" long",
        "location": "",
        "quantity": "1.00",
        "stockcode": "11220"
    },
    {
        "description": "Microswitch plate",
        "location": "",
        "quantity": "2.00",
        "stockcode": "11349"
    },
    {
        "description": "Stepper Motor 1.8 degrees",
        "location": "",
        "quantity": "1.00",
        "stockcode": "18045"
    },
    {
        "description": "Female Screw Lock Assembly 13mm Long",
        "location": "",
        "quantity": "2.00",
        "stockcode": "19044"
    }
]