[
    {
        "description": "ITRI 50mm Sphere Entrance Plate",
        "location": "",
        "quantity": "1.00",
        "stockcode": "44324_P1"
    },
    {
        "description": "ITRI Ø50MM SPHERE BAFFLE",
        "location": "",
        "quantity": "1.00",
        "stockcode": "44325"
    },
    {
        "description": "D8-50-ITRI Port End Plate",
        "location": "",
        "quantity": "1.00",
        "stockcode": "46131_P1"
    },
    {
        "description": "D8-50-ITRI Ø50MM SPHERE QC DOVETAIL",
        "location": "",
        "quantity": "1.00",
        "stockcode": "46132"
    },
    {
        "description": "ITRI Ø50MM SPHERE BAFFLE",
        "location": "",
        "quantity": "1.00",
        "stockcode": "46133"
    },
    {
        "description": "INLINE 50mm SPHERE BODY",
        "location": "",
        "quantity": "1.00",
        "stockcode": "48089"
    },
    {
        "description": "DIFF-D8-INLINE BUILD MANUAL",
        "location": "",
        "quantity": "1.00",
        "stockcode": "51002-BM"
    },
    {
        "description": "DIFF-D8-INLINE PARTS LIST",
        "location": "",
        "quantity": "1.00",
        "stockcode": "51002-PL"
    },
    {
        "description": "INLINE 50mm BENFLECT HEMISPHERE",
        "location": "",
        "quantity": "1.00",
        "stockcode": "99026-P3"
    },
    {
        "description": "M2.5 x 8, cap head, SS",
        "location": "",
        "quantity": "0.00",
        "stockcode": "99119"
    },
    {
        "description": "M3 x 12 Black Socket Cap Head Screw",
        "location": "",
        "quantity": "0.00",
        "stockcode": "99156"
    },
    {
        "description": "M3 x 3, cone grub, black",
        "location": "",
        "quantity": "0.00",
        "stockcode": "99192"
    }
]